{"key":"12/2010/1241","points":[{"id":"osm:node:10144656602","latitude":57.6489013,"longitude":-3.314023,"name":"High Street near Commerce Street","properties":{"access":"yes","bicycle_pa":"stands","capacity":4,"covered":"no","fee":"no","operator":"","nameSource":"junction"},"sourceId":"osm"},{"id":"osm:node:10202294916","latitude":57.6471883,"longitude":-3.3191578,"name":"Batchen Lane near Thunderton Place","properties":{"access":"yes","bicycle_pa":"stands","capacity":4,"covered":"no","fee":"","operator":"","nameSource":"junction"},"sourceId":"osm"},{"id":"osm:node:10218672280","latitude":57.6500718,"longitude":-3.3171896,"name":"Trinity Road near Trinity Place","properties":{"access":"customers","bicycle_pa":"stands","capacity":6,"covered":"no","fee":"","operator":"Aldi","nameSource":"junction"},"sourceId":"osm"},{"id":"osm:node:10226315404","latitude":57.6513749,"longitude":-3.3237696,"name":"Haugh Road by Moray Leisure Centre","properties":{"access":"unknown","bicycle_pa":"stands","capacity":22,"covered":"no","fee":"","operator":"","nameSource":"landmark"},"sourceId":"osm"},{"id":"osm:node:10616409753","latitude":57.6492081,"longitude":-3.2997219,"name":"Grampian Road cycle parking","properties":{"access":"unknown","bicycle_pa":"stands","capacity":0,"covered":"","fee":"","operator":"","nameSource":"street"},"sourceId":"osm"},{"id":"osm:node:10832374837","latitude":57.6418385,"longitude":-3.3099758,"name":"Edgar Road by Asda Café","properties":{"access":"unknown","bicycle_pa":"","capacity":0,"covered":"","fee":"","operator":"","nameSource":"landmark"},"sourceId":"osm"},{"id":"osm:node:1233883574","latitude":57.6358349,"longitude":-3.2955102,"name":"Thornhill Drive by Glassgreen Dental","properties":{"access":"yes","bicycle_pa":"","capacity":0,"covered":"yes","fee":"","operator":"","nameSource":"landmark"},"sourceId":"osm"},{"id":"osm:node:1663414421","latitude":57.64878,"longitude":-3.3110058,"name":"Glover Street near High Street","properties":{"access":"unknown","bicycle_pa":"stands","capacity":4,"covered":"no","fee":"","operator":"","nameSource":"junction"},"sourceId":"osm"},{"id":"osm:way:1100685281","latitude":57.64872762,"longitude":-3.3098650800000002,"name":"High Street near South College Street","properties":{"access":"unknown","bicycle_pa":"lockers","capacity":15,"covered":"yes","fee":"","operator":"Moray Council","nameSource":"junction"},"sourceId":"osm"},{"id":"osm:way:1100685282","latitude":57.64870614,"longitude":-3.30972274,"name":"High Street near South College Street","properties":{"access":"unknown","bicycle_pa":"shed","capacity":0,"covered":"","fee":"","operator":"Moray Council","nameSource":"junction"},"sourceId":"osm"},{"id":"osm:way:1100685283","latitude":57.64867464,"longitude":-3.3098909400000003,"name":"High Street near South College Street","properties":{"access":"unknown","bicycle_pa":"shed","capacity":0,"covered":"","fee":"","operator":"Moray Council","nameSource":"junction"},"sourceId":"osm"},{"id":"osm:way:1155624325","latitude":57.65278152,"longitude":-3.3282489400000004,"name":"Elgin Academy cycle parking","properties":{"access":"unknown","bicycle_pa":"shed","capacity":0,"covered":"","fee":"","operator":"","nameSource":"landmark"},"sourceId":"osm"},{"id":"osm:way:1155624326","latitude":57.65274008,"longitude":-3.3283050200000006,"name":"Elgin Academy cycle parking","properties":{"access":"unknown","bicycle_pa":"shed","capacity":0,"covered":"","fee":"","operator":"","nameSource":"landmark"},"sourceId":"osm"},{"id":"osm:way:1155624327","latitude":57.65272414,"longitude":-3.32816256,"name":"Elgin Academy cycle parking","properties":{"access":"unknown","bicycle_pa":"shed","capacity":0,"covered":"","fee":"","operator":"","nameSource":"landmark"},"sourceId":"osm"},{"id":"osm:way:1155624328","latitude":57.65309642,"longitude":-3.328996,"name":"Morriston Road near Lang Walk","properties":{"access":"unknown","bicycle_pa":"shed","capacity":0,"covered":"","fee":"","operator":"","nameSource":"junction"},"sourceId":"osm"},{"id":"osm:way:1155624329","latitude":57.6531896,"longitude":-3.3291026799999996,"name":"Morriston Road near Lang Walk","properties":{"access":"unknown","bicycle_pa":"shed","capacity":0,"covered":"","fee":"","operator":"","nameSource":"junction"},"sourceId":"osm"},{"id":"osm:way:1155624330","latitude":57.65316382000001,"longitude":-3.32916278,"name":"Lang Walk near Morriston Road","properties":{"access":"unknown","bicycle_pa":"shed","capacity":0,"covered":"","fee":"","operator":"","nameSource":"junction"},"sourceId":"osm"},{"id":"osm:way:1155624331","latitude":57.65378244,"longitude":-3.32713106,"name":"Morriston Road cycle parking","properties":{"access":"unknown","bicycle_pa":"shed","capacity":0,"covered":"","fee":"","operator":"","nameSource":"street"},"sourceId":"osm"},{"id":"osm:way:1155624332","latitude":57.65376139999999,"longitude":-3.3271936999999996,"name":"Morriston Road cycle parking","properties":{"access":"unknown","bicycle_pa":"shed","capacity":0,"covered":"","fee":"","operator":"","nameSource":"street"},"sourceId":"osm"},{"id":"osm:way:1155624333","latitude":57.65374709999999,"longitude":-3.327236,"name":"Morriston Road cycle parking","properties":{"access":"unknown","bicycle_pa":"shed","capacity":0,"covered":"","fee":"","operator":"","nameSource":"street"},"sourceId":"osm"},{"id":"osm:way:1155624334","latitude":57.653724880000006,"longitude":-3.32730206,"name":"Morriston Road cycle parking","properties":{"access":"unknown","bicycle_pa":"shed","capacity":0,"covered":"","fee":"","operator":"","nameSource":"street"},"sourceId":"osm"},{"id":"osm:way:1157485275","latitude":57.64537392,"longitude":-3.33030434,"name":"Pluscarden Road cycle parking","properties":{"access":"yes","bicycle_pa":"shed","capacity":0,"covered":"yes","fee":"no","operator":"","nameSource":"street"},"sourceId":"osm"},{"id":"osm:way:1177318480","latitude":57.64294828,"longitude":-3.3116919400000002,"name":"Station Road near South Guildry Street","properties":{"access":"unknown","bicycle_pa":"rack","capacity":0,"covered":"yes","fee":"","operator":"","nameSource":"junction"},"sourceId":"osm"},{"id":"osm:way:1177318482","latitude":57.64293752,"longitude":-3.3115462199999994,"name":"Station Road near South Guildry Street","properties":{"access":"unknown","bicycle_pa":"lockers","capacity":5,"covered":"yes","fee":"","operator":"","nameSource":"junction"},"sourceId":"osm"},{"id":"osm:way:1177318483","latitude":57.642897760000004,"longitude":-3.3115392999999997,"name":"Station Road by Elgin Railway Station","properties":{"access":"unknown","bicycle_pa":"stands","capacity":6,"covered":"yes","fee":"","operator":"","nameSource":"landmark"},"sourceId":"osm"},{"id":"osm:way:1194869040","latitude":57.64739852,"longitude":-3.30616128,"name":"Institution Road near Queen Street","properties":{"access":"unknown","bicycle_pa":"shed","capacity":0,"covered":"","fee":"","operator":"","nameSource":"junction"},"sourceId":"osm"}],"schemaVersion":2}
