{"key":"12/2031/1350","points":[{"id":"osm:node:5833530523","latitude":52.111499,"longitude":-1.4607713,"name":"Home Farm Drive cycle parking","properties":{"access":"unknown","bicycle_pa":"stands","capacity":8,"covered":"no","fee":"","operator":"","nameSource":"street"},"sourceId":"osm"},{"id":"osm:node:7343522294","latitude":52.1282304,"longitude":-1.4223259,"name":"Camp Lane cycle parking","properties":{"access":"unknown","bicycle_pa":"shed","capacity":0,"covered":"","fee":"","operator":"","nameSource":"street"},"sourceId":"osm"}],"schemaVersion":2}
