{"key":"12/2015/1274","points":[{"id":"osm:node:11132250068","latitude":56.0383628,"longitude":-2.8415644,"name":"Gullane cycle parking","properties":{"access":"unknown","bicycle_pa":"stands","capacity":6,"covered":"no","fee":"no","operator":"","nameSource":"place"},"sourceId":"osm"},{"id":"osm:node:8718726761","latitude":56.0344057,"longitude":-2.8325294,"name":"Main Street near Saltcoats Road","properties":{"access":"unknown","bicycle_pa":"stands","capacity":10,"covered":"no","fee":"","operator":"","nameSource":"junction"},"sourceId":"osm"}],"schemaVersion":1}
