{"key":"12/1931/1353","points":[{"id":"osm:node:12188450864","latitude":51.9476386,"longitude":-10.2210185,"name":"New Market Street by Spar Express","properties":{"access":"unknown","bicycle_pa":"wall_loops","capacity":3,"covered":"no","fee":"","operator":"","nameSource":"landmark"},"sourceId":"osm"},{"id":"osm:node:12188450865","latitude":51.9476293,"longitude":-10.2210535,"name":"New Market Street by Spar Express","properties":{"access":"unknown","bicycle_pa":"wall_loops","capacity":3,"covered":"yes","fee":"","operator":"","nameSource":"landmark"},"sourceId":"osm"}],"schemaVersion":2}
