{"key":"12/2023/1359","points":[{"id":"osm:node:12735744703","latitude":51.6377459,"longitude":-2.1558947,"name":"Tetbury Trail by Whistle Stop Cafe","properties":{"access":"unknown","bicycle_pa":"stands","capacity":6,"covered":"no","fee":"","operator":"","nameSource":"landmark"},"sourceId":"osm"},{"id":"osm:node:4939128390","latitude":51.6367038,"longitude":-2.1596134,"name":"Church Street near Chipping Street","properties":{"access":"unknown","bicycle_pa":"stands","capacity":2,"covered":"no","fee":"","operator":"","nameSource":"junction"},"sourceId":"osm"},{"id":"osm:node:6299484444","latitude":51.6390167,"longitude":-2.1552787,"name":"Herd Lane near Cirencester Road","properties":{"access":"customers","bicycle_pa":"stands","capacity":0,"covered":"yes","fee":"","operator":"The Royal Oak Tetbury","nameSource":"junction"},"sourceId":"osm"}],"schemaVersion":2}
