{"key":"12/2064/1344","points":[{"id":"osm:node:11659576769","latitude":52.4556246,"longitude":1.4367961,"name":"Castle Orchard by Bungay Shopper","properties":{"access":"unknown","bicycle_pa":"stands","capacity":12,"covered":"","fee":"","operator":"","nameSource":"landmark"},"sourceId":"osm"},{"id":"osm:node:11668604165","latitude":52.4505997,"longitude":1.450154,"name":"Hillside Road East by The Co-operative","properties":{"access":"unknown","bicycle_pa":"stands","capacity":8,"covered":"no","fee":"","operator":"","nameSource":"landmark"},"sourceId":"osm"},{"id":"osm:node:13877530780","latitude":52.4566823,"longitude":1.436286,"name":"Cork Bricks near Earsham Street","properties":{"access":"unknown","bicycle_pa":"stands","capacity":5,"covered":"no","fee":"no","operator":"","nameSource":"junction"},"sourceId":"osm"},{"id":"osm:node:8914906971","latitude":52.4564496,"longitude":1.4343911,"name":"Earsham Street near Outney Road","properties":{"access":"unknown","bicycle_pa":"stands","capacity":8,"covered":"no","fee":"no","operator":"","nameSource":"junction"},"sourceId":"osm"}],"schemaVersion":2}
