{"key":"12/1951/1518","points":[{"id":"osm:node:11160580783","latitude":42.1068625,"longitude":-8.4530082,"name":"A Lamela cycle parking","properties":{"access":"yes","bicycle_pa":"wall_loops","capacity":12,"covered":"no","fee":"no","operator":"","nameSource":"place"},"sourceId":"osm"},{"id":"osm:node:11160580793","latitude":42.1061985,"longitude":-8.4530761,"name":"A Lamela cycle parking","properties":{"access":"yes","bicycle_pa":"wall_loops","capacity":0,"covered":"no","fee":"no","operator":"","nameSource":"place"},"sourceId":"osm"},{"id":"osm:node:11160584606","latitude":42.1045957,"longitude":-8.4598335,"name":"Os Morouzóns cycle parking","properties":{"access":"yes","bicycle_pa":"wall_loops","capacity":12,"covered":"no","fee":"no","operator":"","nameSource":"place"},"sourceId":"osm"},{"id":"osm:node:11160584614","latitude":42.1053437,"longitude":-8.4551309,"name":"A Roda cycle parking","properties":{"access":"yes","bicycle_pa":"wall_loops","capacity":6,"covered":"no","fee":"no","operator":"","nameSource":"place"},"sourceId":"osm"},{"id":"osm:node:11160584663","latitude":42.1044798,"longitude":-8.4598154,"name":"Os Morouzóns cycle parking","properties":{"access":"yes","bicycle_pa":"wall_loops","capacity":12,"covered":"no","fee":"no","operator":"","nameSource":"place"},"sourceId":"osm"},{"id":"osm:node:11160584671","latitude":42.1015906,"longitude":-8.4629697,"name":"Os Morouzóns cycle parking","properties":{"access":"yes","bicycle_pa":"wall_loops","capacity":0,"covered":"no","fee":"no","operator":"","nameSource":"place"},"sourceId":"osm"},{"id":"osm:node:11160584676","latitude":42.1054538,"longitude":-8.4551712,"name":"A Roda cycle parking","properties":{"access":"yes","bicycle_pa":"wall_loops","capacity":6,"covered":"no","fee":"no","operator":"","nameSource":"place"},"sourceId":"osm"}],"schemaVersion":2}
