{"key":"12/2042/1318","points":[{"id":"osm:node:9223886521","latitude":53.8331938,"longitude":-0.4394719,"name":"Refectory cycle parking","properties":{"access":"private","bicycle_pa":"building","capacity":100,"covered":"","fee":"","operator":"","nameSource":"landmark"},"sourceId":"osm"},{"id":"osm:node:9983218821","latitude":53.8044414,"longitude":-0.4664888,"name":"Folly Lake Cafe cycle parking","properties":{"access":"unknown","bicycle_pa":"wall_loops","capacity":10,"covered":"","fee":"","operator":"","nameSource":"landmark"},"sourceId":"osm"}],"schemaVersion":2}
