{"key":"12/1975/1566","points":[{"id":"osm:node:10296798889","latitude":38.9168432,"longitude":-6.3394021,"name":"Paseo de José María Álvarez Sáez de Buruaga near Calle José Ramón Mélida","properties":{"access":"unknown","bicycle_pa":"stands","capacity":5,"covered":"no","fee":"","operator":"","nameSource":"junction"},"sourceId":"osm"},{"id":"osm:node:10297131729","latitude":38.9100782,"longitude":-6.3502565,"name":"Avenida Vicente Sos Maynat near Travesía Eduardo Hernández Pacheco","properties":{"access":"unknown","bicycle_pa":"wall_loops","capacity":6,"covered":"no","fee":"","operator":"","nameSource":"junction"},"sourceId":"osm"},{"id":"osm:node:10297131731","latitude":38.9113545,"longitude":-6.3512547,"name":"Avenida Vicente Sos Maynat cycle parking","properties":{"access":"unknown","bicycle_pa":"wall_loops","capacity":6,"covered":"no","fee":"","operator":"","nameSource":"street"},"sourceId":"osm"},{"id":"osm:node:10297131786","latitude":38.9103152,"longitude":-6.350683,"name":"Avenida Vicente Sos Maynat near Travesía Eduardo Hernández Pacheco","properties":{"access":"unknown","bicycle_pa":"wall_loops","capacity":6,"covered":"no","fee":"","operator":"","nameSource":"junction"},"sourceId":"osm"},{"id":"osm:node:10298105633","latitude":38.9166116,"longitude":-6.3460085,"name":"Plaza de España near Calle Félix Valverde Lillo","properties":{"access":"unknown","bicycle_pa":"stands","capacity":5,"covered":"no","fee":"","operator":"","nameSource":"junction"},"sourceId":"osm"},{"id":"osm:node:10299002482","latitude":38.918016,"longitude":-6.3430509,"name":"Plaza Puerta de la Villa near Calle Delgado Valencia","properties":{"access":"unknown","bicycle_pa":"","capacity":0,"covered":"","fee":"","operator":"","nameSource":"junction"},"sourceId":"osm"},{"id":"osm:node:12291597376","latitude":38.9165739,"longitude":-6.347606,"name":"Plaza de Santa María near Calle de Juan Macías","properties":{"access":"unknown","bicycle_pa":"stands","capacity":12,"covered":"no","fee":"","operator":"","nameSource":"junction"},"sourceId":"osm"},{"id":"osm:node:12291604389","latitude":38.9158381,"longitude":-6.3482567,"name":"Calle Morería near Calle Arquitas","properties":{"access":"unknown","bicycle_pa":"stands","capacity":12,"covered":"no","fee":"","operator":"","nameSource":"junction"},"sourceId":"osm"},{"id":"osm:node:1534813704","latitude":38.9066579,"longitude":-6.3383547,"name":"Avenida Santa Teresa de Jesús Jornet near Calle Antonio García Bellido","properties":{"access":"unknown","bicycle_pa":"","capacity":6,"covered":"","fee":"","operator":"","nameSource":"junction"},"sourceId":"osm"},{"id":"osm:node:1672334202","latitude":38.9168607,"longitude":-6.3722387,"name":"Ciudad deportiva cycle parking","properties":{"access":"unknown","bicycle_pa":"","capacity":0,"covered":"","fee":"","operator":"","nameSource":"landmark"},"sourceId":"osm"},{"id":"osm:node:1673946259","latitude":38.9122458,"longitude":-6.3612411,"name":"BiciMer","properties":{"access":"unknown","bicycle_pa":"","capacity":0,"covered":"","fee":"","operator":"","nameSource":"source"},"sourceId":"osm"},{"id":"osm:node:1674032942","latitude":38.915913,"longitude":-6.3560852,"name":"BiciMer","properties":{"access":"unknown","bicycle_pa":"","capacity":0,"covered":"","fee":"","operator":"","nameSource":"source"},"sourceId":"osm"},{"id":"osm:node:5782773553","latitude":38.918606,"longitude":-6.33615,"name":"Calle Cabo Verde near Calle Pontezuelas","properties":{"access":"unknown","bicycle_pa":"","capacity":0,"covered":"","fee":"","operator":"","nameSource":"junction"},"sourceId":"osm"}],"schemaVersion":2}
