{"key":"12/2046/1344","points":[{"id":"osm:node:699224565","latitude":52.4556184,"longitude":-0.112783,"name":"Raymon Road near Kingfisher Way","properties":{"access":"unknown","bicycle_pa":"stands","capacity":36,"covered":"no","fee":"no","operator":"","nameSource":"junction"},"sourceId":"osm"},{"id":"osm:node:8866883013","latitude":52.4493264,"longitude":-0.1070027,"name":"Great Whyte near New Road","properties":{"access":"unknown","bicycle_pa":"stands","capacity":6,"covered":"no","fee":"","operator":"","nameSource":"junction"},"sourceId":"osm"},{"id":"osm:node:8866920219","latitude":52.4500612,"longitude":-0.107633,"name":"Great Whyte near Rudds Court","properties":{"access":"unknown","bicycle_pa":"stands","capacity":6,"covered":"no","fee":"","operator":"","nameSource":"junction"},"sourceId":"osm"},{"id":"osm:way:1342705977","latitude":52.44886448,"longitude":-0.107854,"name":"Darling Mews near Great Whyte","properties":{"access":"yes","bicycle_pa":"shed","capacity":10,"covered":"yes","fee":"no","operator":"","nameSource":"junction"},"sourceId":"osm"}],"schemaVersion":2}
