{"key":"12/1990/1384","points":[{"id":"osm:node:10159140300","latitude":50.2619363,"longitude":-5.0686388,"name":"Station Road by Argos","properties":{"access":"unknown","bicycle_pa":"stands","capacity":16,"covered":"yes","fee":"","operator":"","nameSource":"landmark"},"sourceId":"osm"},{"id":"osm:node:13426793867","latitude":50.2650241,"longitude":-5.053889,"name":"Pydar Street near St Clement Street","properties":{"access":"unknown","bicycle_pa":"stands","capacity":6,"covered":"no","fee":"","operator":"","nameSource":"junction"},"sourceId":"osm"},{"id":"osm:node:13620432574","latitude":50.2644375,"longitude":-5.0527959,"name":"Pydar Street near Union Place","properties":{"access":"unknown","bicycle_pa":"stands","capacity":8,"covered":"no","fee":"","operator":"","nameSource":"junction"},"sourceId":"osm"},{"id":"osm:node:13794083533","latitude":50.2560307,"longitude":-5.0419692,"name":"Trevelva Road near Pendeen Road","properties":{"access":"unknown","bicycle_pa":"","capacity":0,"covered":"","fee":"","operator":"","nameSource":"junction"},"sourceId":"osm"},{"id":"osm:node:13929069109","latitude":50.2652141,"longitude":-5.0904994,"name":"Occupational Health cycle parking","properties":{"access":"unknown","bicycle_pa":"shed","capacity":0,"covered":"","fee":"","operator":"","nameSource":"landmark"},"sourceId":"osm"},{"id":"osm:node:13929069126","latitude":50.2664878,"longitude":-5.0916675,"name":"Royal Cornwall Hospital cycle parking","properties":{"access":"unknown","bicycle_pa":"shed","capacity":0,"covered":"","fee":"","operator":"","nameSource":"landmark"},"sourceId":"osm"},{"id":"osm:node:13929069250","latitude":50.2676574,"longitude":-5.0922952,"name":"Penventinnie Lane by The Cove Macmillan Support Centre","properties":{"access":"unknown","bicycle_pa":"shed","capacity":0,"covered":"","fee":"","operator":"","nameSource":"landmark"},"sourceId":"osm"},{"id":"osm:node:688510032","latitude":50.2638875,"longitude":-5.0629799,"name":"Brunel Court by Car Club Parking","properties":{"access":"customers","bicycle_pa":"stands","capacity":6,"covered":"no","fee":"no","operator":"","nameSource":"landmark"},"sourceId":"osm"},{"id":"osm:node:9550617514","latitude":50.2616463,"longitude":-5.0541733,"name":"Charles Street near Infirmary Hill","properties":{"access":"unknown","bicycle_pa":"","capacity":2,"covered":"","fee":"no","operator":"","nameSource":"junction"},"sourceId":"osm"},{"id":"osm:node:9555130328","latitude":50.2627525,"longitude":-5.0540487,"name":"Calenick Street near Kenwyn Street","properties":{"access":"customers","bicycle_pa":"stands","capacity":2,"covered":"","fee":"","operator":"","nameSource":"junction"},"sourceId":"osm"},{"id":"osm:node:9571453710","latitude":50.2635442,"longitude":-5.049634,"name":"St Mary's Street near Duke Street","properties":{"access":"unknown","bicycle_pa":"stands","capacity":2,"covered":"no","fee":"","operator":"","nameSource":"junction"},"sourceId":"osm"},{"id":"osm:node:9571456047","latitude":50.263546,"longitude":-5.0496398,"name":"St Mary's Street near Duke Street","properties":{"access":"unknown","bicycle_pa":"stands","capacity":2,"covered":"no","fee":"","operator":"","nameSource":"junction"},"sourceId":"osm"},{"id":"osm:node:9576130552","latitude":50.2618467,"longitude":-5.0480729,"name":"Morlaix Avenue near Lemon Quay","properties":{"access":"yes","bicycle_pa":"stands","capacity":6,"covered":"no","fee":"no","operator":"Cornwall Council","nameSource":"junction"},"sourceId":"osm"},{"id":"osm:node:9576496952","latitude":50.2618583,"longitude":-5.0490244,"name":"Lemon Quay near Morlaix Avenue","properties":{"access":"yes","bicycle_pa":"stands","capacity":5,"covered":"no","fee":"no","operator":"","nameSource":"junction"},"sourceId":"osm"},{"id":"osm:node:9576496953","latitude":50.2618844,"longitude":-5.0491156,"name":"Lemon Quay near Morlaix Avenue","properties":{"access":"yes","bicycle_pa":"stands","capacity":5,"covered":"no","fee":"no","operator":"","nameSource":"junction"},"sourceId":"osm"},{"id":"osm:node:9588561382","latitude":50.2640997,"longitude":-5.0523276,"name":"High Cross near King Street","properties":{"access":"yes","bicycle_pa":"stands","capacity":2,"covered":"no","fee":"no","operator":"","nameSource":"junction"},"sourceId":"osm"},{"id":"osm:node:9588561387","latitude":50.2639938,"longitude":-5.0522625,"name":"High Cross near King Street","properties":{"access":"yes","bicycle_pa":"stands","capacity":2,"covered":"no","fee":"no","operator":"","nameSource":"junction"},"sourceId":"osm"},{"id":"osm:node:9609821680","latitude":50.2618351,"longitude":-5.0568713,"name":"Bassett Walk cycle parking","properties":{"access":"yes","bicycle_pa":"stands","capacity":2,"covered":"","fee":"no","operator":"","nameSource":"street"},"sourceId":"osm"},{"id":"osm:way:1041479786","latitude":50.26370609999999,"longitude":-5.053041262500001,"name":"The Leats near Tonkins Ope","properties":{"access":"yes","bicycle_pa":"stands","capacity":16,"covered":"no","fee":"no","operator":"","nameSource":"junction"},"sourceId":"osm"},{"id":"osm:way:1043565444","latitude":50.25979256,"longitude":-5.048113720000001,"name":"Morlaix Avenue by Aldi","properties":{"access":"unknown","bicycle_pa":"","capacity":0,"covered":"","fee":"","operator":"","nameSource":"landmark"},"sourceId":"osm"},{"id":"osm:way:1094633189","latitude":50.26792314000001,"longitude":-5.0932032000000005,"name":"Penventinnie Lane by The Duchy Hospital","properties":{"access":"private","bicycle_pa":"","capacity":0,"covered":"","fee":"","operator":"","nameSource":"landmark"},"sourceId":"osm"}],"schemaVersion":2}
