{"key":"12/2087/1554","points":[{"categories":["hire"],"id":"osm:node:4312990243","latitude":39.7165196,"longitude":3.4603902,"name":"Schulz","properties":{"operator":"Miguel Angel Schulz","website":"http://schulzrentabike.com/"},"sourceId":"osm"},{"categories":["hire"],"id":"osm:node:4332360166","latitude":39.7100784,"longitude":3.457156,"name":"Cristóbal","properties":{"website":"http://rentabike-cristobal.com/"},"sourceId":"osm"},{"categories":["hire"],"id":"osm:node:6644759874","latitude":39.7078335,"longitude":3.4566724,"name":"Schulz","properties":{"website":"http://schulzrentabike.com/"},"sourceId":"osm"},{"categories":["hire"],"id":"osm:node:6644759875","latitude":39.707222,"longitude":3.4570007,"name":"Cristóbal","properties":{"website":"http://rentabike-cristobal.com/"},"sourceId":"osm"},{"categories":["hire"],"id":"osm:node:6644759876","latitude":39.717405,"longitude":3.460003,"name":"Cristóbal","properties":{"website":"http://rentabike-cristobal.com/"},"sourceId":"osm"}],"schemaVersion":2}
