{"key":"12/2033/1370","points":[{"categories":["repair"],"id":"osm:node:12349087958","latitude":51.0513939,"longitude":-1.3053663,"name":"Bicycle repair station","properties":{"fee":"no","openingHours":"24/7"},"sourceId":"osm"},{"categories":["shop","repair","hire"],"id":"osm:node:4814412147","latitude":51.062563,"longitude":-1.3117003,"name":"Exo - The Winchester Bike Hub","properties":{"openingHours":"Mo-Sa 09:00-17:00; Su 09:00-16:00","operator":"The Winchester Bike Hub CIC","servicePump":"yes","serviceRental":"yes","serviceRepair":"yes"},"sourceId":"osm"},{"categories":["repair"],"id":"osm:node:4907707326","latitude":51.0569204,"longitude":-1.2350323,"name":"Bicycle repair station","properties":{"servicePump":"yes"},"sourceId":"osm"},{"categories":["repair"],"id":"osm:node:7969536916","latitude":51.0494763,"longitude":-1.3111113,"name":"Bicycle repair station","properties":{"servicePump":"yes"},"sourceId":"osm"},{"categories":["shop","repair"],"id":"osm:way:1160233051","latitude":51.06211595,"longitude":-1.31133395,"name":"Bikex","properties":{"openingHours":"mo-su 10-6","operator":"Bikex","servicePump":"yes","serviceRepair":"yes","serviceTools":"yes"},"sourceId":"osm"},{"categories":["shop"],"id":"osm:way:374179298","latitude":51.061015028571425,"longitude":-1.3070352285714286,"name":"Cytronex","properties":{},"sourceId":"osm"}],"schemaVersion":2}
