{"key":"12/2048/1367","points":[{"id":"osm:node:1492515567","latitude":51.1999862,"longitude":0.0672631,"name":"Station Approach by Edenbridge Town","properties":{"access":"unknown","bicycle_pa":"stands","capacity":10,"covered":"yes","fee":"","operator":"","nameSource":"landmark"},"sourceId":"osm"},{"id":"osm:node:1492518005","latitude":51.1975886,"longitude":0.0645755,"name":"High Street near Croft Lane","properties":{"access":"unknown","bicycle_pa":"stands","capacity":8,"covered":"no","fee":"","operator":"","nameSource":"junction"},"sourceId":"osm"},{"id":"osm:node:1492520601","latitude":51.1972165,"longitude":0.0648622,"name":"High Street near Croft Lane","properties":{"access":"unknown","bicycle_pa":"stands","capacity":8,"covered":"no","fee":"","operator":"","nameSource":"junction"},"sourceId":"osm"}],"schemaVersion":2}
