{"key":"12/2028/1375","points":[{"id":"osm:node:11004384671","latitude":50.7813199,"longitude":-1.735833,"name":"Betsy Lane near Bransgore Parade","properties":{"access":"unknown","bicycle_pa":"stands","capacity":6,"covered":"no","fee":"","operator":"","nameSource":"junction"},"sourceId":"osm"},{"id":"osm:node:1988790588","latitude":50.7409983,"longitude":-1.7451911,"name":"Somerford Road near Wilverley Road","properties":{"access":"unknown","bicycle_pa":"stands","capacity":6,"covered":"no","fee":"","operator":"","nameSource":"junction"},"sourceId":"osm"},{"id":"osm:node:2174158989","latitude":50.7421195,"longitude":-1.6973607,"name":"Lymington Road near Gordon Road","properties":{"access":"unknown","bicycle_pa":"stands","capacity":4,"covered":"no","fee":"","operator":"","nameSource":"junction"},"sourceId":"osm"},{"id":"osm:node:2174159041","latitude":50.7374229,"longitude":-1.6925488,"name":"Highcliffe-on-Sea cycle parking","properties":{"access":"unknown","bicycle_pa":"stands","capacity":12,"covered":"no","fee":"","operator":"","nameSource":"place"},"sourceId":"osm"},{"id":"osm:node:2174159098","latitude":50.737815,"longitude":-1.6951773,"name":"Waterford Road by Highcliffe Beach","properties":{"access":"unknown","bicycle_pa":"stands","capacity":10,"covered":"no","fee":"","operator":"","nameSource":"landmark"},"sourceId":"osm"},{"id":"osm:node:2174159145","latitude":50.7409909,"longitude":-1.6991551,"name":"Wortley Road cycle parking","properties":{"access":"unknown","bicycle_pa":"stands","capacity":8,"covered":"no","fee":"","operator":"","nameSource":"street"},"sourceId":"osm"},{"id":"osm:node:2174159379","latitude":50.7421348,"longitude":-1.6973003,"name":"Lymington Road near Gordon Road","properties":{"access":"unknown","bicycle_pa":"stands","capacity":4,"covered":"no","fee":"","operator":"","nameSource":"junction"},"sourceId":"osm"},{"id":"osm:node:2174159383","latitude":50.7420958,"longitude":-1.6974545,"name":"Lymington Road near Gordon Road","properties":{"access":"unknown","bicycle_pa":"stands","capacity":4,"covered":"no","fee":"","operator":"","nameSource":"junction"},"sourceId":"osm"},{"id":"osm:node:2203863915","latitude":50.7449809,"longitude":-1.7397019,"name":"Lyndhurst Road by New Forest Bacon and Local Meats","properties":{"access":"unknown","bicycle_pa":"stands","capacity":8,"covered":"no","fee":"","operator":"","nameSource":"landmark"},"sourceId":"osm"},{"id":"osm:node:2203889874","latitude":50.7370655,"longitude":-1.7148316,"name":"Highcliffe Castle Car Park cycle parking","properties":{"access":"unknown","bicycle_pa":"stands","capacity":8,"covered":"","fee":"","operator":"","nameSource":"landmark"},"sourceId":"osm"},{"id":"osm:node:2203889906","latitude":50.7372276,"longitude":-1.712392,"name":"Zig Zag Path cycle parking","properties":{"access":"unknown","bicycle_pa":"stands","capacity":8,"covered":"","fee":"","operator":"","nameSource":"street"},"sourceId":"osm"},{"id":"osm:node:2330779972","latitude":50.7366484,"longitude":-1.7110058,"name":"Zig Zag Path cycle parking","properties":{"access":"unknown","bicycle_pa":"stands","capacity":6,"covered":"no","fee":"","operator":"","nameSource":"street"},"sourceId":"osm"},{"id":"osm:node:2413912883","latitude":50.7432584,"longitude":-1.7400914,"name":"Lyndhurst Road by KFC","properties":{"access":"unknown","bicycle_pa":"stands","capacity":12,"covered":"no","fee":"","operator":"","nameSource":"landmark"},"sourceId":"osm"},{"id":"osm:node:5488717532","latitude":50.7500844,"longitude":-1.6895264,"name":"Walkford Road near Wyndham Road","properties":{"access":"unknown","bicycle_pa":"stands","capacity":2,"covered":"no","fee":"","operator":"","nameSource":"junction"},"sourceId":"osm"},{"id":"osm:node:5508826709","latitude":50.7404666,"longitude":-1.6881158,"name":"Glenside near The Park","properties":{"access":"unknown","bicycle_pa":"stands","capacity":4,"covered":"no","fee":"","operator":"","nameSource":"junction"},"sourceId":"osm"},{"id":"osm:node:5508826710","latitude":50.7405515,"longitude":-1.6871368,"name":"Glendrive near Bartonside Road","properties":{"access":"unknown","bicycle_pa":"wall_loops","capacity":6,"covered":"no","fee":"","operator":"","nameSource":"junction"},"sourceId":"osm"},{"id":"osm:node:5656766967","latitude":50.7438858,"longitude":-1.7416801,"name":"Christchurch Bypass by Timpson","properties":{"access":"unknown","bicycle_pa":"stands","capacity":9,"covered":"yes","fee":"","operator":"","nameSource":"landmark"},"sourceId":"osm"},{"id":"osm:node:5734955114","latitude":50.7525353,"longitude":-1.7131148,"name":"Station Road near Hinton Wood Avenue","properties":{"access":"unknown","bicycle_pa":"stands","capacity":20,"covered":"yes","fee":"","operator":"","nameSource":"junction"},"sourceId":"osm"},{"id":"osm:node:7775711915","latitude":50.7400066,"longitude":-1.6880562,"name":"The Park near Glenside","properties":{"access":"unknown","bicycle_pa":"stands","capacity":18,"covered":"no","fee":"","operator":"","nameSource":"junction"},"sourceId":"osm"},{"id":"osm:node:7795081531","latitude":50.7413287,"longitude":-1.7426119,"name":"Somerford Road by Matalan","properties":{"access":"unknown","bicycle_pa":"stands","capacity":8,"covered":"no","fee":"","operator":"","nameSource":"landmark"},"sourceId":"osm"},{"id":"osm:node:9115190569","latitude":50.7456016,"longitude":-1.7046748,"name":"Greenways near Denham Drive","properties":{"access":"private","bicycle_pa":"","capacity":0,"covered":"no","fee":"no","operator":"","nameSource":"junction"},"sourceId":"osm"},{"id":"osm:way:1074911372","latitude":50.74032604,"longitude":-1.7047235200000004,"name":"Wharncliffe Road near Beacon Drive","properties":{"access":"yes","bicycle_pa":"rack","capacity":0,"covered":"no","fee":"no","operator":"","nameSource":"junction"},"sourceId":"osm"},{"id":"osm:way:1074917787","latitude":50.742428939999996,"longitude":-1.6977029399999999,"name":"Lymington Road by Tesco Express","properties":{"access":"private","bicycle_pa":"shed","capacity":4,"covered":"yes","fee":"no","operator":"","nameSource":"landmark"},"sourceId":"osm"},{"id":"osm:way:985993644","latitude":50.73833668,"longitude":-1.75504414,"name":"Bingham Road cycle parking","properties":{"access":"unknown","bicycle_pa":"shed","capacity":0,"covered":"yes","fee":"","operator":"","nameSource":"street"},"sourceId":"osm"},{"id":"osm:way:986692565","latitude":50.740399849999996,"longitude":-1.7567893,"name":"Draper Road near Redvers Road","properties":{"access":"private","bicycle_pa":"","capacity":0,"covered":"yes","fee":"no","operator":"","nameSource":"junction"},"sourceId":"osm"}],"schemaVersion":2}
